django_postgresql_dag/exceptions.py
django_postgresql_dag/models.py
django_postgresql_dag/query_builders.py
django_postgresql_dag/transformations.py
django_postgresql_dag/urls.py
django_postgresql_dag/utils.py
django_postgresql_dag-0.4.0.dist-info/LICENSE
django_postgresql_dag-0.4.0.dist-info/WHEEL
django_postgresql_dag-0.4.0.dist-info/METADATA
django_postgresql_dag-0.4.0.dist-info/RECORD
