Metadata-Version: 2.1
Name: django-postgresql-dag
Version: 0.4.0
Summary: Directed Acyclic Graph implementation for Django & Postgresql
Home-page: https://github.com/OmenApps/django-postgresql-dag
License: MIT
Keywords: django,graph,tree,dag,network,directed,acyclic,postgres,cte
Author: Jack Linke
Author-email: jack@watervize.com
Requires-Python: >=3.8,<4.0
Classifier: Development Status :: 3 - Alpha
Classifier: Environment :: Web Environment
Classifier: Framework :: Django
Classifier: Framework :: Django :: 3
Classifier: Framework :: Django :: 3.2
Classifier: Framework :: Django :: 4
Classifier: Framework :: Django :: 4.0
Classifier: Framework :: Django :: 4.1
Classifier: Intended Audience :: Developers
Classifier: License :: OSI Approved :: MIT License
Classifier: Programming Language :: Python :: 3
Classifier: Programming Language :: Python :: 3.8
Classifier: Programming Language :: Python :: 3.9
Classifier: Programming Language :: Python :: 3.10
Classifier: Programming Language :: Python :: 3.11
Classifier: Programming Language :: Python :: 3
Classifier: Programming Language :: Python :: 3 :: Only
Requires-Dist: django (>=3.2)
Requires-Dist: psycopg2-binary (>=2.9,<3.0)
Project-URL: Documentation, https://django-postgresql-dag.readthedocs.io/en/latest/
Project-URL: Repository, https://github.com/OmenApps/django-postgresql-dag
